usp/__init__.py
usp/cli/__init__.py
usp/cli/_ls.py
usp/cli/_util.py
usp/cli/cli.py
usp/exceptions.py
usp/fetch_parse.py
usp/helpers.py
usp/objects/__init__.py
usp/objects/page.py
usp/objects/sitemap.py
usp/py.typed
usp/tree.py
usp/web_client/__init__.py
usp/web_client/abstract_client.py
usp/web_client/requests_client.py
ultimate_sitemap_parser-1.8.0.dist-info/licenses/LICENSE
ultimate_sitemap_parser-1.8.0.dist-info/licenses/NOTICE
ultimate_sitemap_parser-1.8.0.dist-info/WHEEL
ultimate_sitemap_parser-1.8.0.dist-info/entry_points.txt
ultimate_sitemap_parser-1.8.0.dist-info/METADATA
ultimate_sitemap_parser-1.8.0.dist-info/RECORD
