Metadata-Version: 2.4
Name: ultimate-sitemap-parser
Version: 1.8.0
Summary: A performant library for parsing and crawling sitemaps
Keywords: sitemap,crawler,indexing,xml,rss,atom,google news
Author: Linas Valiukas, Hal Roberts, Freddy Heppell
Author-email: Linas Valiukas <linas@media.mit.edu>, Hal Roberts <hroberts@cyber.law.harvard.edu>, Freddy Heppell <f.heppell@sheffield.ac.uk>
License-Expression: GPL-3.0-or-later
License-File: LICENSE
License-File: NOTICE
Classifier: Development Status :: 5 - Production/Stable
Classifier: Intended Audience :: Developers
Classifier: Intended Audience :: Information Technology
Classifier: License :: OSI Approved :: GNU General Public License v3 or later (GPLv3+)
Classifier: Programming Language :: Python
Classifier: Operating System :: OS Independent
Classifier: Topic :: Internet :: WWW/HTTP :: Indexing/Search
Classifier: Topic :: Text Processing :: Indexing
Classifier: Topic :: Text Processing :: Markup :: XML
Classifier: Programming Language :: Python :: 3
Classifier: Programming Language :: Python :: 3.10
Classifier: Programming Language :: Python :: 3.11
Classifier: Programming Language :: Python :: 3.12
Classifier: Programming Language :: Python :: 3.13
Classifier: Programming Language :: Python :: 3.14
Requires-Dist: python-dateutil>=2.7,<3.0.0
Requires-Dist: requests>=2.2.1,<3.0.0
Maintainer: Freddy Heppell
Maintainer-email: Freddy Heppell <f.heppell@sheffield.ac.uk>
Requires-Python: >=3.10
Project-URL: homepage, https://ultimate-sitemap-parser.readthedocs.io/
Project-URL: documentation, https://ultimate-sitemap-parser.readthedocs.io/
Project-URL: repository, https://github.com/GateNLP/ultimate-sitemap-parser
